{
  "country_code": "PH",
  "country_name": "Philippines",
  "geo_type": "province_state",
  "destination": "Cebu",
  "link": "https://luxuryescapes.com/search?destinationName=Cebu&destinationId=le_dacebfb5d91ee0388e78c9133972e0bf&adults=2&children=none&pages=2",
  "affiliate_link": "https://luxuryescapes.com/search?destinationName=Cebu&destinationId=le_dacebfb5d91ee0388e78c9133972e0bf&adults=2&children=none&pages=2&utm_source=mondoexplora&utm_medium=affiliate&utm_campaign=route&affiliate_id=mondoexplora_001"
}