{
  "country_code": "IN",
  "country_name": "India",
  "geo_type": "province_state",
  "destination": "Goa",
  "link": "https://luxuryescapes.com/search?destinationName=Goa&destinationId=le_ba1ceaceb2db0e0462679cfc4a6ae170&adults=2&children=none&pages=2",
  "affiliate_link": "https://luxuryescapes.com/search?destinationName=Goa&destinationId=le_ba1ceaceb2db0e0462679cfc4a6ae170&adults=2&children=none&pages=2&utm_source=mondoexplora&utm_medium=affiliate&utm_campaign=route&affiliate_id=mondoexplora_001"
}