{
  "country_code": "TH",
  "country_name": "Thailand",
  "geo_type": "city",
  "destination": "Karon",
  "link": "https://luxuryescapes.com/search?destinationName=Karon&destinationId=le_b4cc02b6fd96dc538e79abf48132bb3c&adults=2&children=none&pages=2",
  "affiliate_link": "https://luxuryescapes.com/search?destinationName=Karon&destinationId=le_b4cc02b6fd96dc538e79abf48132bb3c&adults=2&children=none&pages=2&utm_source=mondoexplora&utm_medium=affiliate&utm_campaign=route&affiliate_id=mondoexplora_001"
}