{
  "country_code": "SG",
  "country_name": "Singapore",
  "geo_type": "high_level_region",
  "destination": "Sentosa Island",
  "link": "https://luxuryescapes.com/search?destinationName=Sentosa+Island&destinationId=le_e049cdf2bfe4dd1d825ada227d1479f2&adults=2&children=none&pages=2",
  "affiliate_link": "https://luxuryescapes.com/search?destinationName=Sentosa+Island&destinationId=le_e049cdf2bfe4dd1d825ada227d1479f2&adults=2&children=none&pages=2&utm_source=mondoexplora&utm_medium=affiliate&utm_campaign=route&affiliate_id=mondoexplora_001"
}