{
  "name": "Djibouti",
  "code": "DJ",
  "hero_title": "Djibouti Travel Guide",
  "description": "Scopri la perfetta fusione di cultura, lusso e avventura in Djibouti.",
  "hero_image": "https://images.luxuryescapes.com/ggi1xtgawgmyfklo8oc",
  "popular_destinations": [
    {
      "name": "Djibouti",
      "slug": "djibouti",
      "image": "https://images.luxuryescapes.com/ggi1xtgawgmyfklo8oc",
      "description": "Explore Djibouti with luxury accommodations"
    }
  ],
  "seo": {
    "title": "Djibouti Hotels & Travel Guide 2024",
    "description": "Trova i migliori hotel in Djibouti con offerte esclusive. Esplora alloggi di lusso e guide di viaggio.",
    "keywords": [
      "djibouti hotels",
      "djibouti travel",
      "djibouti luxury"
    ],
    "canonical": "https://mondoexplora.com/it/country/dj",
    "hreflang": {
      "en": "https://mondoexplora.com/en/country/dj",
      "es": "https://mondoexplora.com/es/country/dj",
      "fr": "https://mondoexplora.com/fr/country/dj",
      "it": "https://mondoexplora.com/it/country/dj"
    }
  }
}