{
  "city": "Cheshire",
  "country": "United Kingdom",
  "country_code": "GB",
  "hero_title": "Hotels in Cheshire",
  "description": "Discover the best hotels in Cheshire, United Kingdom. Find exclusive deals and luxury accommodations.",
  "hero_image": "https://images.luxuryescapes.com/0iu8c5k4ipr7ux09o5ol",
  "hotels": [
    {
      "vendor_name": "Crewe Hall Hotel & Spa",
      "offer_country_name": "United Kingdom",
      "location_heading": "Cheshire",
      "title": "17th-Century Mansion Retreat in Fairytale Cheshire",
      "description": "For a splash of wow-factor, enjoy a stay at Crewe Hall Hotel & Spa, a stunning 17th-century Grade I-listed Jacobean mansion in picturesque Cheshire. Upon entering the manicured grounds, feel like you've stepped back to a time of opulence and splendour: discover period-style interiors with ornate ceilings and rich furnishings, plus an atmospheric Brasserie Bar and Lounge to enjoy an exquisite meal, and the elegant Sheridan Lounge to feast on Crewe Hall's famous afternoon tea. While the hotel celebrates its heritage roots, the modern comforts of the 21st century haven't been forgotten. Relax with a treatment at the spa, take a dip in the heated indoor swimming pool and swing into your escape with a round of tennis on the onsite courts.",
      "location_subheading": "United Kingdom",
      "price": 97,
      "original_price": 97,
      "discount_percentage": 0,
      "link": "https://luxuryescapes.com/offer/0062y0000070uywAAA",
      "hero_image": "https://images.luxuryescapes.com/0iu8c5k4ipr7ux09o5ol",
      "image_two": "https://images.luxuryescapes.com/gpornu2vffxampo5ljp4",
      "image_three": "https://images.luxuryescapes.com/z08jzdt6v80x5zd54h2",
      "deal_tier": "Luxury Escapes - Tier 3",
      "min_duration": 1,
      "end_date_utc": "2026-12-31 12:59:00"
    },
    {
      "vendor_name": "The Park Royal Hotel & Spa",
      "offer_country_name": "United Kingdom",
      "location_heading": "Cheshire",
      "title": "Contemporary Spa Retreat in the Cheshire Countryside",
      "description": "Settle in for a cosy yet contemporary stay at The Park Royal Hotel & Spa, perfectly set in the charming village of Stretton in leafy Cheshire. Within close reach of the hotel, you can unearth some of the country’s best pubs, shopping precincts and attractions, with Chester, Liverpool and Manchester all an easy drive away. Feel immediately at home as you drop your bags within one of the stylish rooms and admire the ornate architecture that dates back as far as 1831. Choose to spend hours at the indulgent spa, complete a few laps of the heated pool, then retire each night to Topiary in the Park restaurant, the casual Lounge Bar or the outdoor terrace.",
      "location_subheading": "United Kingdom",
      "price": 86,
      "original_price": 86,
      "discount_percentage": 0,
      "link": "https://luxuryescapes.com/offer/0062y000007lrjgAAA",
      "hero_image": "https://images.luxuryescapes.com/f5lm5v8r5fn4btc3by",
      "image_two": "https://images.luxuryescapes.com/49e6w5st3d7422ui4ne",
      "image_three": "https://images.luxuryescapes.com/xqxtm95nsq50ezoko9hg",
      "deal_tier": "Luxury Escapes - Tier 3",
      "min_duration": 1,
      "end_date_utc": "2026-12-31 12:59:00"
    }
  ],
  "seo": {
    "title": "Hotels in Cheshire - United Kingdom Hotels & Travel Guide 2024",
    "description": "Find the best hotels in Cheshire, United Kingdom with exclusive deals. Book your perfect getaway with up to 60% off.",
    "keywords": [
      "cheshire hotels",
      "cheshire travel",
      "united kingdom hotels"
    ],
    "canonical": "https://mondoexplora.com/en/destination/cheshire",
    "hreflang": {
      "en": "https://mondoexplora.com/en/destination/cheshire",
      "es": "https://mondoexplora.com/es/destination/cheshire",
      "fr": "https://mondoexplora.com/fr/destination/cheshire",
      "it": "https://mondoexplora.com/it/destination/cheshire"
    }
  },
  "meta": {
    "last_updated": "2025-07-27",
    "hotel_count": 2,
    "average_price": 92,
    "average_discount": 0
  }
}