{
  "city": "Kooddoo Island",
  "country": "Maldives",
  "country_code": "MV",
  "hero_title": "Hoteles en Kooddoo Island",
  "description": "Descubre los mejores hoteles en Kooddoo Island, Maldives. Encuentra ofertas exclusivas y alojamientos de lujo.",
  "hero_image": "https://images.luxuryescapes.com/6h3mmxilsmotee3ncs7rl",
  "hotels": [
    {
      "vendor_name": "Mercure Maldives Kooddoo",
      "offer_country_name": "Maldives",
      "location_heading": "Kooddoo Island",
      "title": "Maldives All-Inclusive Oasis: Adults-Only Bliss with Free-Flow Drinks & Domestic Flight Transfers",
      "description": "Surrender to the allure of the Maldives at this award-winning oasis that feels worlds away from the everyday. Just a 60-minute domestic flight from Malé, the Gaafu Alifu Atoll awaits, surrounded by an ocean so vividly blue it defies imagination. At Mercure Maldives Kooddoo Resort, indulge in all-inclusive luxury with drinks, meals, snacks and an in-villa minibar. Culinary delights abound, with international flavours at Alita restaurant and authentic Italian dishes at the overwater restaurant Vista. Unwind with a handcrafted cocktail at the Pool Bar before retreating to your private island haven. Each moment here is crafted to deliver quality experiences in a setting of unparalleled natural beauty. Immerse yourself in this unspoilt paradise, a long-standing favourite with honeymooners. Relax at the serene Suvadiva Spa, or snorkel through the pristine underwater wonders of the atoll. As an adults-only resort, this retreat offers the ultimate escape where you can bask in breathtaking sunsets and enjoy uninterrupted peace with your loved one.",
      "location_subheading": "Maldives",
      "price": 2239,
      "original_price": 6585,
      "discount_percentage": 66,
      "link": "https://luxuryescapes.com/offer/006RF00000JDtGgYAL",
      "hero_image": "https://images.luxuryescapes.com/6h3mmxilsmotee3ncs7rl",
      "image_two": "https://images.luxuryescapes.com/r33vy2u8yhvbwp9fxe7q",
      "image_three": "https://images.luxuryescapes.com/rmtzpcrsz8t3coeizpon",
      "deal_tier": "Luxury Escapes - Tier 1",
      "min_duration": 5,
      "end_date_utc": "2025-08-08 13:59:00"
    }
  ],
  "seo": {
    "title": "Hoteles en Kooddoo Island - Maldives Hotels & Travel Guide 2024",
    "description": "Encuentra los mejores hoteles en Kooddoo Island, Maldives con ofertas exclusivas. Reserva tu escapada perfecta con hasta 60% de descuento.",
    "keywords": [
      "kooddoo island hotels",
      "kooddoo island travel",
      "maldives hotels"
    ],
    "canonical": "https://mondoexplora.com/es/destination/kooddoo-island",
    "hreflang": {
      "en": "https://mondoexplora.com/en/destination/kooddoo-island",
      "es": "https://mondoexplora.com/es/destination/kooddoo-island",
      "fr": "https://mondoexplora.com/fr/destination/kooddoo-island",
      "it": "https://mondoexplora.com/it/destination/kooddoo-island"
    }
  },
  "meta": {
    "last_updated": "2025-07-27",
    "hotel_count": 1,
    "average_price": 2239,
    "average_discount": 66
  }
}