[
  {
    "link": "https://luxuryescapes.com/offer/0062y00000DI5w2AAD",
    "hero_image": "https://images.luxuryescapes.com/70racnmzpddxxyxy2k15",
    "image_two": "https://images.luxuryescapes.com/drzyq3i49vnyta6aoop",
    "image_three": "https://images.luxuryescapes.com/ne3r8i669rred9wns03",
    "vendor_name": "Holiday Inn Calais",
    "title": "Refreshing Calais Harbour Stay near Beach & Ferry Port",
    "description": "Savour views of the Strait of Dover and the sound of lapping waves when you stay at Holiday Inn Calais, an IHG Hotel. This modern hotel is located within arm's reach of the city's most significant destinations, including the Ferry Port, Notre-Dame church, Museum of Fine Arts and the golden shores of Calais Beach. When you're not exploring, stay in and enjoy a bite at the hotel's harbour-view restaurant which serves up French cuisine alongside your favourite breakfast items daily.",
    "offer_country_name": "France",
    "offer_country_code_alpha_2": "FR",
    "offer_geo_area_level_1": "Hauts-de-France",
    "offer_geo_area_level_2": "Calais",
    "location_heading": "Calais",
    "location_subheading": "France",
    "location_description": "Holiday Inn Calais, an IHG Hotel",
    "offer_address": "6 Boulevard des Alliés, Calais, 62100, France",
    "percentage_discount": 0.0,
    "min_duration": 1,
    "max_duration": 30,
    "price": 74.0,
    "value": 74.0
  }
]