[
  {
    "link": "https://luxuryescapes.com/offer/0060I00000d0OM7QAM",
    "hero_image": "https://images.luxuryescapes.com/fh8adfzya6mr8293dvg",
    "image_two": "https://images.luxuryescapes.com/tdekcu7lcrql8s33d4z",
    "image_three": "https://images.luxuryescapes.com/8lo0odrvhjw2y3ffao7q",
    "vendor_name": "QT Falls Creek",
    "title": "Boutique Summer Luxury in the Victorian High Country",
    "description": "Hike through rolling green hills, ascend soaring mountains and escape in style to the award-winning QT Falls Creek with a romantic weekend escape. A boutique five-star retreat in the Victorian hills, this adventurer’s dream getaway includes daily à la carte breakfast, a complimentary bottle of sparkling wine and chocolates on arrival, unlimited on-demand movies and guaranteed 1pm late checkout so you can take your time revelling in the serene High Country atmosphere.",
    "offer_country_name": "Australia",
    "offer_country_code_alpha_2": "AU",
    "offer_geo_area_level_1": "Victoria",
    "offer_geo_area_level_2": "Falls Creek",
    "location_heading": "Falls Creek",
    "location_subheading": "Victoria",
    "location_description": "QT Falls Creek",
    "offer_address": "17 Bogong High Plains Rd, Falls Creek VIC 3699",
    "percentage_discount": 33.0,
    "min_duration": 2,
    "max_duration": 3,
    "price": 321.0,
    "value": 482.0
  },
  {
    "link": "https://luxuryescapes.com/offer/0062y0000037JkEAAU",
    "hero_image": "https://images.luxuryescapes.com/nbbzws2tnzmfy5d77cs",
    "image_two": "https://images.luxuryescapes.com/gejjas411k08mfn0n6z64",
    "image_three": "https://images.luxuryescapes.com/ntxyp8yd8ibvt6tkwxx55",
    "vendor_name": "QT Falls Creek",
    "title": "QT Alpine Luxury with Balcony Hot Tub",
    "description": "Wake up to the bliss of mountain mist and uninterrupted valley views in a boutique apartment at QT Falls Creek. The ultimate hikers’ paradise in summer, this Victorian High Country escape delivers vintage chalet chic and alpine elegance all year round.\n\nWith a steamy outdoor hotel spa and a private hot tub on every balcony, romance abounds at this top-tier hotel. Make the most of the incredible QT facilities including the indoor plunge pool and spa, ski lodge-inspired Stingray Lounge, the stressless paradise of spaQ and the Bazaar - a unique marketplace dining experience.\n\nYour handpicked inclusions:\n\n- Guaranteed upgrade to a One-Bedroom Spa Apartment with a hot tub on the balcony\n- Daily continental breakfast at the après ski-inspired Stingray Lounge\n- One welcome drink per adult at the Stingray Lounge\n- Make the most of every moment with a guaranteed 1pm late checkout",
    "offer_country_name": "Australia",
    "offer_country_code_alpha_2": "AU",
    "offer_geo_area_level_1": "Victoria",
    "offer_geo_area_level_2": "Falls Creek",
    "location_heading": "Falls Creek",
    "location_subheading": "Victoria",
    "location_description": "QT Falls Creek",
    "offer_address": "17 Bogong High Plains Rd, Falls Creek VIC 3699",
    "percentage_discount": null,
    "min_duration": 1,
    "max_duration": 7,
    "price": null,
    "value": null
  }
]