[
  {
    "link": "https://luxuryescapes.com/offer/0062y00000AaQp7AAF",
    "hero_image": "https://images.luxuryescapes.com/gsew6p6377q6cx07ydc",
    "image_two": "https://images.luxuryescapes.com/6ztjjeohjvq8sr4g52u6",
    "image_three": "https://images.luxuryescapes.com/w9visttfwd6p4fnzmjp",
    "vendor_name": "Montage Big Sky",
    "title": "Glamorous Ski-In, Ski-Out Montana Mountain Retreat with 10,000-Square-Foot Spa",
    "description": "The natural beauty of Montana's Big Sky Country is front and centre at the area's first five-star resort, Montage Big Sky, a majestic ski-in/ski-out mountain retreat. During winter, the mountains are dusted with a thick blanket of snow, and in summer, the resort offers recreational activities including a private 18-hole golf course designed by Tom Weiskopf. The 10,000-square-foot Spa Montage promises a transcendent pampering experience, with alpine-inspired treatments and heated plunge pools. Onsite dining is a celebration of culinary excellence: savour pre-dinner cocktails with live piano music at Alpenglow, dine on traditional Northern Italian cuisine at Cortina and feast on wood-fired pizzas between bowling rounds at the fun-filled Beartooth Pub & Rec.",
    "offer_country_name": "United States",
    "offer_country_code_alpha_2": "US",
    "offer_geo_area_level_1": "Montana",
    "offer_geo_area_level_2": "Big Sky",
    "location_heading": "Montana",
    "location_subheading": "United States",
    "location_description": "Montage Big Sky",
    "offer_address": "995 Settlement Trail, Big Sky, Montana 59716, United States",
    "percentage_discount": 0.0,
    "min_duration": 1,
    "max_duration": 30,
    "price": 466.0,
    "value": 466.0
  },
  {
    "link": "https://luxuryescapes.com/offer/0062y00000EdKFjAAN",
    "hero_image": "https://images.luxuryescapes.com/d4w5b13vmhh3chblybmk",
    "image_two": "https://images.luxuryescapes.com/er5hcztajf1el5k5xm2s",
    "image_three": "https://images.luxuryescapes.com/z6tckn37376x1twn4pz",
    "vendor_name": "Kimpton Armory Hotel Bozeman",
    "title": "Historic Art Deco Bozeman Montana Stay with Music Hall, Rooftop Pool & Scenic Bars & Restaurants",
    "description": "Experience the best of Bozeman with a stay at the Kimpton Armory Hotel Bozeman, an IHG Hotel, housed in the Art Deco former National Guard Armory building. Taste hearty fare at onsite tavern Fielding's, sip whiskey at Tune Up, look out over the snowcapped Montana mountains at the rooftop Sky Shed bar, or take in a live music show at the onsite Armory Music Hall. Outdoor enthusiasts will savour the proximity to world-class hiking and skiing opportunities just moments away.",
    "offer_country_name": "United States",
    "offer_country_code_alpha_2": "US",
    "offer_geo_area_level_1": "Montana",
    "offer_geo_area_level_2": "Bozeman",
    "location_heading": "Montana",
    "location_subheading": "United States",
    "location_description": "Kimpton Armory Hotel Bozeman, an IHG Hotel",
    "offer_address": "24 W. Mendenhall Street, Bozeman, Montana 59715, United States",
    "percentage_discount": 0.0,
    "min_duration": 1,
    "max_duration": 30,
    "price": 209.0,
    "value": 209.0
  }
]