[
  {
    "link": "https://luxuryescapes.com/offer/0060I00000cqJmkQAE",
    "hero_image": "https://images.luxuryescapes.com/2vcd25zngmuw9b3a2gno",
    "image_two": "https://images.luxuryescapes.com/k0peq3upu9xjs6tsjk8",
    "image_three": "https://images.luxuryescapes.com/rs4wy2ny9rtfyn9z7jl",
    "vendor_name": "Rayong Marriott Resort & Spa",
    "title": "City Lights to Seaside Bliss: From Bangkok to Rayong in Marriott Luxury",
    "description": "The ultimate two-in-one escape is here: experience the best of both worlds with this ultimate, easy-to-plan Thai holiday, taking you from bustling Bangkok to beachfront Rayong. Spend two nights in vibrant Bangkok at the five-star Bangkok Marriott Marquis Queen’s Park, then indulge in pure beachfront relaxation at the luxurious Rayong Marriott Resort & Spa. Enjoy daily international buffet breakfast in both hotels, plus daily dining, 30-minute massages and cocktails in Rayong - a hidden gem situated just three hours' drive from Bangkok, showcasing a more authentic side of Thailand.\n\nTravel in VIP style with private transfers to and from the airport, and between both hotels.",
    "offer_country_name": "Thailand",
    "offer_country_code_alpha_2": "TH",
    "offer_geo_area_level_1": "Rayong Province",
    "offer_geo_area_level_2": "Klaeng",
    "location_heading": "Bangkok & Rayong",
    "location_subheading": "Thailand",
    "location_description": "Bangkok Marriott Marquis Queen’s Park & Rayong Marriott Resort & Spa",
    "offer_address": "99/5 Moo 2 Pae-Klaeng-Kram Road, Chakphong, Klaeng District, Rayong 21190, Thailand",
    "percentage_discount": 59.0,
    "min_duration": 4,
    "max_duration": 10,
    "price": 1053.0,
    "value": 2576.0
  }
]