[
  {
    "link": "https://luxuryescapes.com/offer/0062y00000CQJb9AAH",
    "hero_image": "https://images.luxuryescapes.com/dgertry32eo1lbx0wrr",
    "image_two": "https://images.luxuryescapes.com/89dkoto8ygz7q3sjued",
    "image_three": "https://images.luxuryescapes.com/qkwqp5f53rj5f8x198em",
    "vendor_name": "Crowne Plaza London - Kingston",
    "title": "Contemporary Kingston Retreat Overlooking River Thames",
    "description": "Discover the ‘birthplace of England’ and wander through one of the royal boroughs in England and Wales, with a stay at Crowne Plaza London - Kingston, an IHG Hotel. Located overlooking the River Thames, this hotel is the perfect base to attend events including Wimbledon, and explore royal relics and medieval landmarks. Refuel for your day with a hearty buffet breakfast at 360 Restaurant, then end it the most quintessential English way - savouring an evening pint at 360 Bar.",
    "offer_country_name": "United Kingdom",
    "offer_country_code_alpha_2": "GB",
    "offer_geo_area_level_1": "England",
    "offer_geo_area_level_2": "Surbiton",
    "location_heading": "Long Ditton",
    "location_subheading": "United Kingdom",
    "location_description": "Crowne Plaza London - Kingston, an IHG Hotel",
    "offer_address": "Kingston Tower, Portsmouth Road, Long Ditton, Surbiton KT6 5PZ, United Kingdom",
    "percentage_discount": 0.0,
    "min_duration": 1,
    "max_duration": 30,
    "price": 105.0,
    "value": 105.0
  }
]