[
  {
    "link": "https://luxuryescapes.com/offer/0062y00000Bdt5uAAB",
    "hero_image": "https://images.luxuryescapes.com/yrsoj5dpvn8c2suuz6kh",
    "image_two": "https://images.luxuryescapes.com/wequbswuqgajb21jf0em",
    "image_three": "https://images.luxuryescapes.com/zk8bkov3qsii38k2fjfq",
    "vendor_name": "Intercontinental Sao Paulo",
    "title": "Five-Star InterContinental São Paulo Stay with Outdoor Pool & Stylish Cocktail Bar",
    "description": "Located in the chic Jardins neighbourhood, adjacent to hip Pinheiros, the five-star InterContinental São Paulo, an IHG Hotel is idyllically placed for exploring the city's top attractions, cosy cafés and trendy nightlife. Before setting out to explore, stop in at the cosmopolitan Godet Bar for a cocktail, or indulge in São Paulo's famed gastronomy at Tarsila Restaurant. When it comes to leisure, all bases are covered with an outdoor swimming pool, 24-hour fitness centre and a dedicated concierge to help you plan.",
    "offer_country_name": "Brazil",
    "offer_country_code_alpha_2": "BR",
    "offer_geo_area_level_1": "Sao Paulo State",
    "offer_geo_area_level_2": "Sao Paulo",
    "location_heading": "São Paulo",
    "location_subheading": "Brazil",
    "location_description": "InterContinental São Paulo, an IHG Hotel",
    "offer_address": "Alameda Santos 1123, São Paulo, 01419-001, Brazil",
    "percentage_discount": 0.0,
    "min_duration": 1,
    "max_duration": 30,
    "price": 187.0,
    "value": 187.0
  },
  {
    "link": "https://luxuryescapes.com/offer/006RF00000Jjv7sYAB",
    "hero_image": "https://images.luxuryescapes.com/oaf3c3hq7794hddhf142",
    "image_two": "https://images.luxuryescapes.com/kdfoqcz7np4hycq5q57",
    "image_three": "https://images.luxuryescapes.com/zplxnz70us6o4ng04qvd",
    "vendor_name": "Novotel São Paulo Jardins",
    "title": "Modern São Paulo City Escape with Outdoor Pool & Onsite Dining",
    "description": "Experience refined sophistication in the heart of São Paulo’s elegant Jardins district, surrounded by leafy boulevards and designer boutiques. Just steps away, discover the renowned Rua Oscar Freire, home to luxury fashion houses and chic cafes, or wander to Ibirapuera Park for tranquil lakes, sculpture gardens and the Museum of Modern Art.\n\nReturn to contemporary comfort, where the onsite restaurant serves Brazilian classics with a cosmopolitan twist, and the outdoor pool offers sun-soaked relaxation. Explore nearby culinary gems such as D.O.M. by acclaimed chef Alex Atala or enjoy artisanal pastries at Pão bakery on Alameda Lorena.",
    "offer_country_name": "Brazil",
    "offer_country_code_alpha_2": "BR",
    "offer_geo_area_level_1": "Sao Paulo State",
    "offer_geo_area_level_2": "Sao Paulo",
    "location_heading": "São Paulo",
    "location_subheading": "Brazil",
    "location_description": "Novotel São Paulo Jardins",
    "offer_address": "Alameda Campinas, 1435 Jardim Paulista, São Paulo 01404002, Brazil",
    "percentage_discount": 0.0,
    "min_duration": 1,
    "max_duration": 31,
    "price": 70.0,
    "value": 70.0
  }
]