[
  {
    "link": "https://luxuryescapes.com/offer/006RF00000Ib18OYAR",
    "hero_image": "https://images.luxuryescapes.com/drztl7i21rqmahsyzgw",
    "image_two": "https://images.luxuryescapes.com/0xnb48419q1fdr70eez6",
    "image_three": "https://images.luxuryescapes.com/1j5rey8pflhbsvfobpth",
    "vendor_name": "Movenpick Kuwait Al Bidaa",
    "title": "Beachfront Kuwait City Oasis with Three Restaurants, Five Pools & Onsite Spa",
    "description": "Settle into sun-soaked comfort at this beachside escape in Kuwait City, where palm-lined shores and warm Persian Gulf breezes invite you to slow down. With Mediterranean-inspired designs, five sparkling pools, direct beach access, fitness centre overlooking the pool and soothing spa offering a wide range of treatments, relaxation comes easy here.\n\nDining is a highlight - sample local seafood and mixed grills at Beldani Restaurant; indulge in decadent all-day dining at Breeze Restaurant; or relax with baked treats on the sea-facing terrace at Veranda Cafe. After a day of exploring the Kuwait Towers or shopping at Souk Al-Salmiah and Marina World, return to your well-appointed room, suite or villa to unwind in style.",
    "offer_country_name": "Kuwait",
    "offer_country_code_alpha_2": "KW",
    "offer_geo_area_level_1": "Hawalli",
    "offer_geo_area_level_2": "Salmiya",
    "location_heading": "Kuwait City",
    "location_subheading": "Kuwait",
    "location_description": "Mövenpick Hotel & Resort Al Bida’a Kuwait",
    "offer_address": "Salmiya 22084 Al Ta'awen Street, Kuwait City13008, Kuwait",
    "percentage_discount": 0.0,
    "min_duration": 1,
    "max_duration": 31,
    "price": 136.0,
    "value": 136.0
  },
  {
    "link": "https://luxuryescapes.com/offer/0062y00000CQJclAAH",
    "hero_image": "https://images.luxuryescapes.com/r3b6o76vhg22y44m6jhe",
    "image_two": "https://images.luxuryescapes.com/9bqw7qf8aq1ksv5t6br",
    "image_three": "https://images.luxuryescapes.com/3gruezpymfvh7hxkme7j",
    "vendor_name": "Crowne Plaza Kuwait Al Thuraya City",
    "title": "Five-Star Kuwait Glamour with Eight Outstanding Restaurants",
    "description": "Embrace the ancient culture and fascinating sites of Kuwait City from your luxurious base, the five-star Crowne Plaza Kuwait Al Thuraya City, an IHG Hotel. Spend your downtime working out at Kuwait's largest hotel fitness centre, Health Club Edge, or slip into a Spa Aquatonic pool for some well-deserved pampering. You're spoilt for choice when it comes to dining: with eight restaurants onsite, whether you're craving succulent rib eye steak, fresh seafood or teppanyaki, you'll find it here.",
    "offer_country_name": "Kuwait",
    "offer_country_code_alpha_2": "KW",
    "offer_geo_area_level_1": "Farwaniya",
    "offer_geo_area_level_2": "Farwaniya",
    "location_heading": "Kuwait City",
    "location_subheading": "Kuwait",
    "location_description": "Crowne Plaza Kuwait Al Thuraya City, an IHG Hotel",
    "offer_address": "Airport Road, Kuwait City 81006, Kuwait",
    "percentage_discount": 0.0,
    "min_duration": 1,
    "max_duration": 30,
    "price": 158.0,
    "value": 158.0
  }
]