[
  {
    "link": "https://luxuryescapes.com/offer/006RF00000Ib047YAB",
    "hero_image": "https://images.luxuryescapes.com/6u98vd9dnei92s0ykhdh",
    "image_two": "https://images.luxuryescapes.com/k0eygysj07e3cu6ff8bg",
    "image_three": "https://images.luxuryescapes.com/tyi92ar9ocoytgezw4e",
    "vendor_name": "Novotel Lucknow Gomti Nagar",
    "title": "Sleek Lucknow Escape with Rooftop Bar, Infinity Pool & Luxe Spa",
    "description": "Embrace the charm of Lucknow's cultural tapestry from this chic Novotel sanctuary, ideally situated in the heart of Gomti Nagar, the perfect base for exploring the City of Nawabs. Step into spacious, contemporary rooms designed for comfort and unwind at the rooftop infinity-edge pool, or recharge at the spa and fitness centre.\n\nIndulge in signature Awadhi cuisine, delicious kebabs and global favourites at The Square, or sip handcrafted cocktails with sweeping skyline views at The Edge rooftop bar. When it's time to explore, the city's historical gems, including the Bara Imambara and the iconic Rumi Darwaza, are all a short drive away.",
    "offer_country_name": "India",
    "offer_country_code_alpha_2": "IN",
    "offer_geo_area_level_1": "Uttar Pradesh",
    "offer_geo_area_level_2": "Lucknow",
    "location_heading": "Gomti Nagar",
    "location_subheading": "India",
    "location_description": "Novotel Lucknow Gomti Nagar",
    "offer_address": "Viraj Khand-4, Viraj Khand, Gomti Nagar, Lucknow, Uttar Pradesh, 226010, India",
    "percentage_discount": 0.0,
    "min_duration": 1,
    "max_duration": 31,
    "price": 48.0,
    "value": 48.0
  }
]