[
  {
    "link": "https://luxuryescapes.com/offer/006Ii000002HX4AIAW",
    "hero_image": "https://images.luxuryescapes.com/0ccmyn26o969nl7b12j",
    "image_two": "https://images.luxuryescapes.com/pyvpu1wni28pqlztg2cu",
    "image_three": "https://images.luxuryescapes.com/irwtdeqhjkoaknal6b9",
    "vendor_name": "Aspen Meadows Resort",
    "title": "Aspen All-Suite Mountain Retreat with Daily US$50 Dining Credit & Airport Transfers",
    "description": "You're invited to discover the best of Aspen with a stay at this Herbert Bayer-designed resort - an all-suite institution framed by Aspen Mountain and the lush Highlands. This Bauhaus-inspired escape within the USA's most upscale alpine city offers opportunities to chase the rush or relaxation - spend your day speeding down the slopes, or ease tired muscles in the heated outdoor pool and hot tub.\n\nSpend days snowboarding or skiing on some of the country's plushest snow, take advantage of bicycle rentals in the summer to explore the Rio Grande trail, or tuck into locally sourced ingredients from Colorado’s Rocky Mountains at the resort's onsite restaurant, West End Social.",
    "offer_country_name": "United States",
    "offer_country_code_alpha_2": "US",
    "offer_geo_area_level_1": "Colorado",
    "offer_geo_area_level_2": "Aspen",
    "location_heading": "Aspen",
    "location_subheading": "USA",
    "location_description": "Aspen Meadows Resort",
    "offer_address": "845 Meadows Road, Aspen, Colorado 81611, USA",
    "percentage_discount": 51.0,
    "min_duration": 2,
    "max_duration": 14,
    "price": 749.0,
    "value": 1544.0
  },
  {
    "link": "https://luxuryescapes.com/offer/006RF00000IdFODYA3",
    "hero_image": "https://images.luxuryescapes.com/f2485shn24cuefj94lh",
    "image_two": "https://images.luxuryescapes.com/srxuw7gglntmoe6q5k8e",
    "image_three": "https://images.luxuryescapes.com/jza2tdgs1rxwzybmvtl",
    "vendor_name": "Aspen Meadows Resort",
    "title": "Stylish Aspen All-Suite Mountain Retreat with Daily US$50 Dining Credit & Airport Transfers",
    "description": "You're invited to discover the best of Aspen with a stay at this Herbert Bayer-designed resort - an all-suite institution framed by Aspen Mountain and the lush Aspen Highlands. This Bauhaus-inspired escape within the USA's most upscale alpine city offers opportunities to chase the rush or relaxation - spend your day speeding down the slopes, or ease tired muscles in the heated outdoor pool and hot tub.\n\nSpend days snowboarding or skiing on some of the country's plushest snow, then when you're ready to refuel, you can tuck into locally sourced ingredients from Colorado’s Rocky Mountains at the resort's onsite restaurant, West End Social.",
    "offer_country_name": "United States",
    "offer_country_code_alpha_2": "US",
    "offer_geo_area_level_1": "Colorado",
    "offer_geo_area_level_2": "Aspen",
    "location_heading": "Aspen",
    "location_subheading": "USA",
    "location_description": "Aspen Meadows Resort",
    "offer_address": "845 Meadows Road, Aspen, Colorado 81611, USA",
    "percentage_discount": 41.0,
    "min_duration": 2,
    "max_duration": 14,
    "price": 2459.0,
    "value": 4163.0
  }
]