[
  {
    "link": "https://luxuryescapes.com/offer/006Ii000002IYtxIAG",
    "hero_image": "https://images.luxuryescapes.com/t47uxx9z20uixqyajx9",
    "image_two": "https://images.luxuryescapes.com/l9h2yojjaidgcq00h4sy",
    "image_three": "https://images.luxuryescapes.com/4r9evlaecztlktcgbnve",
    "vendor_name": "CABN Hahndorf",
    "title": "Grand Opening: Hahndorf Off-Grid Luxury Eco-Cabin within Adelaide Hills Wine Country",
    "description": "Be one of the first to unplug and unwind at this off-grid eco-sanctuary, a collection of cosy cabins in the Adelaide Hills housed within a natural amphitheatre of native gum trees. Disconnect from the noise and reconnect with the earth's rhythms from the comfort of your modern retreat, boasting a fireplace, barbeque, kitchenette and an outdoor sitting area to enjoy the native flora and fauna from your doorstep.\n\nWith a complete commitment to sustainability, you can rest peacefully knowing the environment surrounding you is cared for, with each cabin powered by the sun and planet-conscious systems in place. Whether you're feeling fit for a hike or looking for a peaceful retreat, make the most of the picturesque bushland on winding walking paths or the Heysen Trail nearby, set against the backdrop of the Mount Lofty Ranges.\n\nVenture further afield to discover the charming German village of Hahndorf with its streets lined with artisan shops, or taste local drops from Shaw and Smith, Sidewood Estate, Hahndorf Hill Winery and Ambleside Distillers in the renowned Adelaide Hills region. Visit the Beerenberg Family farm, where homemade Australian jams, chutneys, relishes and sauces are made, or pick fresh strawberries in the summertime.",
    "offer_country_name": "Australia",
    "offer_country_code_alpha_2": "AU",
    "offer_geo_area_level_1": "South Australia",
    "offer_geo_area_level_2": "Adelaide",
    "location_heading": "Hahndorf",
    "location_subheading": "South Australia",
    "location_description": "CABN Hahndorf",
    "offer_address": "59 Sandow Road, Verdun, South Australia 5245, Australia",
    "percentage_discount": 43.0,
    "min_duration": 2,
    "max_duration": 6,
    "price": 249.0,
    "value": 435.0
  },
  {
    "link": "https://luxuryescapes.com/offer/006RF00000GZ2DqYAL",
    "hero_image": "https://images.luxuryescapes.com/p84qjdvx0cbquj3mtl1",
    "image_two": "https://images.luxuryescapes.com/yxaf8kn02mima1v72j4t",
    "image_three": "https://images.luxuryescapes.com/41udwk7p6pb91zhcj2d",
    "vendor_name": "CABN Hahndorf",
    "title": "Hahndorf Off-Grid Luxury Eco-Cabin within Adelaide Hills Wine Country",
    "description": "Unplug and unwind at this off-grid eco-sanctuary, a collection of cosy cabins in the Adelaide Hills housed within a natural amphitheatre of native gum trees. Disconnect from the noise and reconnect with the earth's rhythms from the comfort of your modern retreat, boasting a fireplace, barbeque, kitchenette and an outdoor sitting area to enjoy the native flora and fauna from your doorstep.\n\nWith a complete commitment to sustainability, you can rest peacefully knowing the environment surrounding you is cared for, with each cabin powered by the sun and planet-conscious systems in place. Whether you're feeling fit for a hike or looking for a peaceful retreat, make the most of the picturesque bushland on winding walking paths or the Heysen Trail nearby, set against the backdrop of the Mount Lofty Ranges.",
    "offer_country_name": "Australia",
    "offer_country_code_alpha_2": "AU",
    "offer_geo_area_level_1": "South Australia",
    "offer_geo_area_level_2": "Adelaide",
    "location_heading": "Hahndorf",
    "location_subheading": "South Australia",
    "location_description": "CABN Hahndorf",
    "offer_address": "59 Sandow Road, Verdun, Hahndorf, Adelaide Hills, South Australia 5245, Australia",
    "percentage_discount": 0.0,
    "min_duration": 1,
    "max_duration": 31,
    "price": 355.0,
    "value": 355.0
  }
]