[
  {
    "link": "https://luxuryescapes.com/offer/0062y000002Lgs5AAC",
    "hero_image": "https://images.luxuryescapes.com/ob5gcrltr7mmjltufvtj",
    "image_two": "https://images.luxuryescapes.com/rmw9lc3ovj4gv7lg6dsq",
    "image_three": "https://images.luxuryescapes.com/1l2sfp31olfz6ky48w",
    "vendor_name": "Town Hall Hotel and Apartments",
    "title": "Boutique London Escape with Daily Breakfast",
    "description": "Discover a different side to London at the historic - with a twist - Town Hall Hotel and Apartments, located in the authentic East End hamlet of Bethnal Green. Just 12 minutes by tube to Oxford Circus, close to the popular V&A Museum of Childhood and filled with quirky coffee shops, trendy restaurants and cocktail bars, this is a location for those who like their city breaks a little different. Stay in boutique luxury and enjoy daily breakfast and a surprise welcome gift on arrival.",
    "offer_country_name": "United Kingdom",
    "offer_country_code_alpha_2": "GB",
    "offer_geo_area_level_1": "England",
    "offer_geo_area_level_2": "London",
    "location_heading": "Bethnal Green",
    "location_subheading": "London",
    "location_description": "Town Hall Hotel and Apartments",
    "offer_address": "8 Patriot Square, London E2 9NF, United Kingdom",
    "percentage_discount": 49.0,
    "min_duration": 3,
    "max_duration": 7,
    "price": 681.0,
    "value": 1334.0
  }
]