[
  {
    "link": "https://luxuryescapes.com/offer/006Ii000002J0hTIAS",
    "hero_image": "https://images.luxuryescapes.com/le9fb2dhlonyy9hm0la",
    "image_two": "https://images.luxuryescapes.com/6l5ogmv0hc1uslyaa39s",
    "image_three": "https://images.luxuryescapes.com/w8949rj7k3k4ohitko5k",
    "vendor_name": "Iconic Santorini, A Boutique Cave Hotel",
    "title": "Santorini Cliffside Oceanfront Resort with Daily Breakfast, Nightly Cocktails & Massages",
    "description": "Get your Greek on with a unique stay at this tranquil retreat perched high above Santorini's historic caldera wall. Carved into the hillside, this haven offers breathtaking views of the deep blue Aegean Sea, rooms that capture the essence of ancient Greek style and architecture, and the Icons Restaurant & Cocktail Bar to unwind and enjoy the island's natural beauty.\n\nWhether you're organising a romantic getaway with a loved one or planning an exceptional holiday with friends, Santorini has plenty of activities to cater to every taste. Enjoy idyllic culinary experiences with seasonal cuisine and local wines, or take a trip to the onsite ICONIC SPA for a touch of wellness during your stay.",
    "offer_country_name": "Greece",
    "offer_country_code_alpha_2": "GR",
    "offer_geo_area_level_1": "South Aegean",
    "offer_geo_area_level_2": "Santorini",
    "location_heading": "Imerovigli",
    "location_subheading": "Greece",
    "location_description": "Iconic Santorini",
    "offer_address": "Imerovigli, Santorini 847 00, Cyclades, Greece",
    "percentage_discount": 52.0,
    "min_duration": 3,
    "max_duration": 24,
    "price": 849.0,
    "value": 1785.0
  },
  {
    "link": "https://luxuryescapes.com/offer/0062y00000JTWUGAA5",
    "hero_image": "https://images.luxuryescapes.com/xait1699uvzn4v3qn44r",
    "image_two": "https://images.luxuryescapes.com/ngruj3os4atfy5so8fjd",
    "image_three": "https://images.luxuryescapes.com/wv3cw81mwn6c8upqqpsj",
    "vendor_name": "Iconic Santorini, A Boutique Cave Hotel",
    "title": "Secluded Santorini Oceanfront Resort Carved into the Cliffs with Panoramic Aegean Views",
    "description": "Get your Greek on with a unique stay at this tranquil, five-star retreat perched high above Santorini's historic caldera wall. Carved into the hillside, this veritable haven offers breathtaking views of the deep blue Aegean Sea, rooms that capture the essence of ancient Greek style and architecture, and the Icons Restaurant & Cocktail Bar to unwind and enjoy the island's natural beauty.\n\nWhether you're organising a romantic getaway with a loved one or planning an exceptional holiday with friends, Santorini has plenty of activities to cater to every taste. Enjoy idyllic culinary experiences with seasonal cuisine and local wines, or take a trip to the onsite ICONIC SPA for a touch of wellness during your stay.",
    "offer_country_name": "Greece",
    "offer_country_code_alpha_2": "GR",
    "offer_geo_area_level_1": "South Aegean",
    "offer_geo_area_level_2": "Santorini",
    "location_heading": "Imerovigli",
    "location_subheading": "Greece",
    "location_description": "Iconic Santorini",
    "offer_address": "Imerovigli, 847 00 Santorini, Cyclades, Greece",
    "percentage_discount": 0.0,
    "min_duration": 1,
    "max_duration": 30,
    "price": 297.0,
    "value": 297.0
  }
]