[
  {
    "link": "https://luxuryescapes.com/offer/0062y00000CQJa9AAH",
    "hero_image": "https://images.luxuryescapes.com/fvs6wf7bse4sw8q54a7",
    "image_two": "https://images.luxuryescapes.com/1t030w2vyk2w4hxnuq2",
    "image_three": "https://images.luxuryescapes.com/th5mwj6wtuyj5yutbmqg",
    "vendor_name": "Crowne Plaza Lanzhou",
    "title": "China Modern Lanzhou Escape with Yellow River Views",
    "description": "Overlooking the Yellow River, Crowne Plaza Lanzhou, an IHG Hotel, is a soaring gateway to this dynamic city. Sample delicacies such as Lanzhou beef noodles at local food stalls before returning for a soothing treatment at the hotel's onsite spa or a refreshing dip in the pool. As the sun sets, dine on traditional cuisine at China Town Restaurant, discover regional Halal dishes at the Persia Specialty Restaurant or savour a refined cocktail at the lobby lounge.",
    "offer_country_name": "China",
    "offer_country_code_alpha_2": "CN",
    "offer_geo_area_level_1": "Gansu",
    "offer_geo_area_level_2": "Lanzhou",
    "location_heading": "Lanzhou",
    "location_subheading": "China",
    "location_description": "Crowne Plaza Lanzhou, an IHG Hotel",
    "offer_address": "No.1 Beibinhe Road East, Chengguan District, Lanzhou 730046, Mainland China",
    "percentage_discount": 0.0,
    "min_duration": 1,
    "max_duration": 30,
    "price": 65.0,
    "value": 65.0
  }
]