[
  {
    "link": "https://luxuryescapes.com/offer/0062y00000CQJaFAAX",
    "hero_image": "https://images.luxuryescapes.com/sz9uv40ko8n59e4ohm3g",
    "image_two": "https://images.luxuryescapes.com/cnzecpice244xs8t1gp",
    "image_three": "https://images.luxuryescapes.com/dek0zsg20mnm5vw8lle9",
    "vendor_name": "Crowne Plaza Marlow",
    "title": "UK Contemporary Marlow Retreat in Heart of Buckinghamshire near River Thames",
    "description": "Let the glorious English countryside capture your heart with a stay at the contemporary Crowne Plaza Marlow, an IHG Hotel, set alongside the River Thames. From this perfect springboard, spend days taking in green surroundings, wandering along bunting-strung streets hiding gastronomic delights, or breathing in fresh air on hiking and cycling routes. Savour contemporary cuisine at Glaze Restaurant, settle in with views of the River Thames or get lost in a tranquil treatment at the hotel’s spa.",
    "offer_country_name": "United Kingdom",
    "offer_country_code_alpha_2": "GB",
    "offer_geo_area_level_1": "England",
    "offer_geo_area_level_2": "Marlow",
    "location_heading": "Marlow",
    "location_subheading": "United Kingdom",
    "location_description": "Crowne Plaza Marlow, an IHG Hotel",
    "offer_address": "Fieldhouse Lane, Marlow SL7 1GJ, United Kingdom",
    "percentage_discount": 0.0,
    "min_duration": 1,
    "max_duration": 30,
    "price": 130.0,
    "value": 130.0
  }
]