[
  {
    "link": "https://luxuryescapes.com/offer/006Ii000002IlvrIAC",
    "hero_image": "https://images.luxuryescapes.com/xy7gx76yygobb5oiec9w",
    "image_two": "https://images.luxuryescapes.com/8v44y7926f5b8sez8y1",
    "image_three": "https://images.luxuryescapes.com/oy4xbq08tt8xc9ibs8r",
    "vendor_name": "Raffles Seychelles",
    "title": "Beachfront Seychelles Private Pool Villas with Five Restaurants & Onsite Spa",
    "description": "Dive into the lap of luxury at this opulent private villa resort, nestled on the island of Praslin, famously known as the 'Garden of Eden'. This island sanctuary puts indulgence centre stage, with just 87 intimate villas that cascade down the hillside, a jaw-dropping ocean-view spa, 24-hour butler service and double infinity pool. Sample the craftsmanship of the island's chefs across five restaurants and bars, enjoying breakfast by the ocean at Losean Restaurant or exquisite seafood at The Sushi Room, or ask your butler to arrange for a sunset picnic on the sand.  \n\nJust a short hop from Mahé, Praslin is your ticket to some of the world's most incredible beaches and rare wildlife. From the picture-perfect sands of Anse Lazio to exploring the ancient wonders of Vallée de Mai, every moment here is a postcard come to life. Unplug and unwind as you're nourished by nature while enjoying the five-star facilities.",
    "offer_country_name": "Seychelles",
    "offer_country_code_alpha_2": "SC",
    "offer_geo_area_level_1": "Baie Sainte Anne",
    "offer_geo_area_level_2": "Praslin Island",
    "location_heading": "Praslin Island",
    "location_subheading": "Seychelles",
    "location_description": "Raffles Seychelles",
    "offer_address": "Anse Takamaka, Praslin, Victoria 0000, Seychelles",
    "percentage_discount": 0.0,
    "min_duration": 1,
    "max_duration": 30,
    "price": 1154.0,
    "value": 1154.0
  }
]