[
  {
    "link": "https://luxuryescapes.com/offer/0060I00000UJ27nQAD",
    "hero_image": "https://images.luxuryescapes.com/s0mpyczqkal0ajzuvzal",
    "image_two": "https://images.luxuryescapes.com/kgddnvtagt5aoaokuw9x",
    "image_three": "https://images.luxuryescapes.com/eodixdzj5orebbsgvmh6",
    "vendor_name": "Rosevears Hotel",
    "title": "Tasmanian Wine Country Escape Near Launceston",
    "description": "Experience the gourmet food, wine and natural beauty of Tasmania’s famous wine region, Tamar River, with a three-night riverside escape at Rosevears Hotel, a 30-minute drive from Launceston Airport. Home to over 30 sprawling wineries, berry farms, local wildlife and secret beaches (where you can spot the world’s smallest penguin), this tranquil part of the world allows you to truly disconnect. Includes a platter of local cheeses, a daily beer or wine each and a late checkout.",
    "offer_country_name": "Australia",
    "offer_country_code_alpha_2": "AU",
    "offer_geo_area_level_1": "Tasmania",
    "offer_geo_area_level_2": "West Tamar Council",
    "location_heading": "Rosevears",
    "location_subheading": "Tasmania",
    "location_description": "Rosevears Hotel 2018",
    "offer_address": "215 Rosevears Dr, Rosevears TAS 7277",
    "percentage_discount": 54.0,
    "min_duration": 3,
    "max_duration": 5,
    "price": 252.0,
    "value": 553.0
  }
]