[
  {
    "link": "https://luxuryescapes.com/offer/0062y00000GdpGpAAJ",
    "hero_image": "https://images.luxuryescapes.com/g45o40bqmu704rh04e2",
    "image_two": "https://images.luxuryescapes.com/jpq7xhples7t7g50s5lr",
    "image_three": "https://images.luxuryescapes.com/lgyg20bsnma191xqivi",
    "vendor_name": "Holiday Inn Resort Szklarska Poreba Happy Valley, an IHG Hotel",
    "title": "Elegant Polish Alps Retreat with Outdoor Pool & Indulgent Day Spa",
    "description": "Hit the slopes with a stay at Holiday Inn Resort Szklarska Poreba Happy Valley, an IHG Hotel, nestled in the heart of Poland's premier ski resort. This mountain retreat is the perfect base all year round - ski trails and snowboarding runs at your doorstep make for thrilling winter days out, while glimmering outdoor pool and forest landscapes offer plenty of fun in the sun. After your adventures, ease weary muscles with a treatment at the onsite spa.",
    "offer_country_name": "Poland",
    "offer_country_code_alpha_2": "PL",
    "offer_geo_area_level_1": "Lower Silesian Voivodeship",
    "offer_geo_area_level_2": "Szklarska Poreba",
    "location_heading": "Szklarska Poreba",
    "location_subheading": "Poland",
    "location_description": "Holiday Inn Resort Szklarska Poreba Happy Valley, an IHG Hotel",
    "offer_address": "Dolna 17, 58-580 Szklarska Poreba, Poland",
    "percentage_discount": null,
    "min_duration": 1,
    "max_duration": 30,
    "price": null,
    "value": null
  }
]