[
  {
    "link": "https://luxuryescapes.com/offer/0062y00000Cv1sRAAR",
    "hero_image": "https://images.luxuryescapes.com/kiwxcno9p4j7favazslc",
    "image_two": "https://images.luxuryescapes.com/o7rywmhvxuq9im1f4jk",
    "image_three": "https://images.luxuryescapes.com/dbguhm2wnfq8s1kx9c5g",
    "vendor_name": "Clayoquot Wilderness Lodge",
    "title": "Vancouver Island Safari-Style Wilderness Oasis with All-Inclusive Dining",
    "description": "Deep in the untouched Vancouver Island hinterlands, you will find unparalleled comfort, fashionably appointed safari-style tents and once-in-a-lifetime experiences at the uber-luxurious Clayoquot Wilderness Lodge. Accessible only by seaplane or private boat, this unique lodging invites guests to discover a sense of inner tranquillity and appreciation for the beauty of Canada’s forestlands. Indulge in all-inclusive dining at the lodge’s sustainable Cookhouse restaurant, or overlook sparkling Clayoquot Sound at The Ivanhoe with a glass of specialty wine. Soothe your body with a waterfront massage or soak in the cedar hot tub at the lodge’s Healing Grounds Spa, known for its restorative treatments and glorious forest views.",
    "offer_country_name": "Canada",
    "offer_country_code_alpha_2": "CA",
    "offer_geo_area_level_1": "British Columbia",
    "offer_geo_area_level_2": "Tofino Inlet",
    "location_heading": "Vancouver Island",
    "location_subheading": "Canada",
    "location_description": "Clayoquot Wilderness Lodge",
    "offer_address": "Bedwell River Valley, Alberni-Clayoquot C, British Columbia V0R 2Z0, Canada",
    "percentage_discount": 0.0,
    "min_duration": 3,
    "max_duration": 14,
    "price": 6134.0,
    "value": 6134.0
  }
]