[
  {
    "link": "https://luxuryescapes.com/offer/0062y00000CQJcgAAH",
    "hero_image": "https://images.luxuryescapes.com/qhv0d7ncqdj7n401sktn",
    "image_two": "https://images.luxuryescapes.com/lhsd8q6nw8z777ajm10r",
    "image_three": "https://images.luxuryescapes.com/lnbzrwr7jlx5vwt20g59",
    "vendor_name": "Crowne Plaza Zhongshan Wing On City",
    "title": "Modern Zhongshan Escape with Spa & Outdoor Pool",
    "description": "Enjoy a comfortable and indulgent stay at the Crowne Plaza Zhongshan Wing On City, an IHG Hotel - a modern haven in an exciting inner-city location. Wander around the bustling South District of Zhongshan's Central Urban Area and explore ancient monuments and famous natural sites, before returning to the hotel's collection of cosy rooms and suites. After your adventures, the spa offers pampering relaxation, and sophisticated fine-dining venues serve up innovative dishes.",
    "offer_country_name": "China",
    "offer_country_code_alpha_2": "CN",
    "offer_geo_area_level_1": "Guangdong",
    "offer_geo_area_level_2": "Zhongshan",
    "location_heading": "Zhongshan",
    "location_subheading": "China",
    "location_description": "Crowne Plaza Zhongshan Wing On City, an IHG Hotel",
    "offer_address": "No.8 XingNan Road, Southern District, Zhongshan 528455, China",
    "percentage_discount": 0.0,
    "min_duration": 1,
    "max_duration": 30,
    "price": 45.0,
    "value": 45.0
  }
]