{
  "city": "Korolevu",
  "country": "Fiji",
  "country_code": "FJ",
  "hero_title": "Hotel a Korolevu",
  "description": "Scopri i migliori hotel a Korolevu, Fiji. Trova offerte esclusive e alloggi di lusso.",
  "hero_image": "https://images.luxuryescapes.com/ripkntbp4rk7d4s8byl",
  "hotels": [
    {
      "vendor_name": "Warwick Fiji",
      "offer_country_name": "Fiji",
      "location_heading": "Korolevu",
      "title": "Five-Star Fiji Coral Coast Oasis with Daily Breakfast & 2 Kids Stay, Play & Eat Free",
      "description": "Surround yourself with the unsurpassed beauty of Fiji’s Coral Coast, where glistening waters, towering palm trees and white sandy beaches provide the perfect setting for an unforgettable escape at the five-star Warwick Fiji. Splash about in the family pool or relax in the adults-only corner, and feel the warm tropical breeze wash over you. Unwind and experience ultimate relaxation at Warwick Fiji’s superior spa - perched on the edge of the ocean overlooking a serene lagoon. Onsite restaurants include the famed Wicked Walu, Japanese restaurant Sazanami, Italian eatery Pappagallo and the buffet-style Bula Brasserie. The Kids’ Club will delight little ones with sandcastle building and treasure hunting, while kayaking, snorkelling, and stand-up paddleboarding is available to the older kids.",
      "location_subheading": "Fiji",
      "price": 221,
      "original_price": 221,
      "discount_percentage": 0,
      "link": "https://luxuryescapes.com/offer/0062y000008gGL1AAM",
      "hero_image": "https://images.luxuryescapes.com/ripkntbp4rk7d4s8byl",
      "image_two": "https://images.luxuryescapes.com/8i6mchasyt0svayvux9",
      "image_three": "https://images.luxuryescapes.com/l6z9pt6s0o69d8sulcwa",
      "deal_tier": "Luxury Escapes - Tier 1",
      "min_duration": 1,
      "end_date_utc": "2050-12-31 12:59:00"
    }
  ],
  "seo": {
    "title": "Hotel a Korolevu - Fiji Hotels & Travel Guide 2024",
    "description": "Trova i migliori hotel a Korolevu, Fiji con offerte esclusive. Prenota la tua fuga perfetta con fino al 60% di sconto.",
    "keywords": [
      "korolevu hotels",
      "korolevu travel",
      "fiji hotels"
    ],
    "canonical": "https://mondoexplora.com/it/destination/korolevu",
    "hreflang": {
      "en": "https://mondoexplora.com/en/destination/korolevu",
      "es": "https://mondoexplora.com/es/destination/korolevu",
      "fr": "https://mondoexplora.com/fr/destination/korolevu",
      "it": "https://mondoexplora.com/it/destination/korolevu"
    }
  },
  "meta": {
    "last_updated": "2025-07-27",
    "hotel_count": 1,
    "average_price": 221,
    "average_discount": 0
  }
}