{
  "city": "Manado",
  "country": "Indonesia",
  "country_code": "ID",
  "hero_title": "Hotel a Manado",
  "description": "Scopri i migliori hotel a Manado, Indonesia. Trova offerte esclusive e alloggi di lusso.",
  "hero_image": "https://images.luxuryescapes.com/a3fsi6bq0i1a8h9ox4ft",
  "hotels": [
    {
      "vendor_name": "Novotel Manado Convention Center",
      "offer_country_name": "Indonesia",
      "location_heading": "Manado",
      "title": "Manado Indonesia Golf Resort Escape with Outdoor Pool & International Restaurant",
      "description": "Nestled on the outskirts of Manado, this hotel invites you to experience tropical sophistication at its finest. With an 18-hole golf course, the resort has endless leisure and recreation opportunities. Refresh in the shimmering outdoor pool, rejuvenate with a pampering spa treatment, or savour mouthwatering international cuisine at The Square restaurant. Positioned between verdant hills and the sparkling Celebes Sea, you're well placed to discover the best of North Sulawesi. Venture to Bunaken National Marine Park for world-renowned diving and snorkelling, hike the trails of the mighty Klabat Volcano, or immerse yourself in the lively culture of Manado's traditional markets.",
      "location_subheading": "Indonesia",
      "price": 32,
      "original_price": 32,
      "discount_percentage": 0,
      "link": "https://luxuryescapes.com/offer/006RF00000CnOvUYAV",
      "hero_image": "https://images.luxuryescapes.com/a3fsi6bq0i1a8h9ox4ft",
      "image_two": "https://images.luxuryescapes.com/o4zkk9e9e9uy3pc12aq",
      "image_three": "https://images.luxuryescapes.com/gxbl7gbtxam8hz5ijs9i",
      "deal_tier": "",
      "min_duration": 1,
      "end_date_utc": "2050-12-31 12:59:00"
    }
  ],
  "seo": {
    "title": "Hotel a Manado - Indonesia Hotels & Travel Guide 2024",
    "description": "Trova i migliori hotel a Manado, Indonesia con offerte esclusive. Prenota la tua fuga perfetta con fino al 60% di sconto.",
    "keywords": [
      "manado hotels",
      "manado travel",
      "indonesia hotels"
    ],
    "canonical": "https://mondoexplora.com/it/destination/manado",
    "hreflang": {
      "en": "https://mondoexplora.com/en/destination/manado",
      "es": "https://mondoexplora.com/es/destination/manado",
      "fr": "https://mondoexplora.com/fr/destination/manado",
      "it": "https://mondoexplora.com/it/destination/manado"
    }
  },
  "meta": {
    "last_updated": "2025-07-27",
    "hotel_count": 1,
    "average_price": 32,
    "average_discount": 0
  }
}