{
  "city": "Daylesford",
  "country": "Australia",
  "country_code": "AU",
  "hero_title": "Hôtels à Daylesford",
  "description": "Découvrez les meilleurs hôtels à Daylesford, Australia. Trouvez des offres exclusives et des hébergements de luxe.",
  "hero_image": "https://images.luxuryescapes.com/kwsgwgqyk0eyibiunyr",
  "hotels": [
    {
      "vendor_name": "Hotel Frangos Daylesford",
      "offer_country_name": "Australia",
      "location_heading": "Daylesford",
      "title": "Boutique Daylesford Spa Country Retreat Just 90 Minutes from Melbourne with Daily Breakfast",
      "description": "Embrace Daylesford's majestic natural scenery with a boutique Parisian-style stay, only a 90-minute drive from Melbourne. A private haven of just 15 unique rooms, Hotel Frangos offers the perfect retreat for those wanting to leave the hustle and bustle behind and experience the tranquillity of picturesque country Victoria. Spend your time taste-testing the local wine at one of the region's many vineyards, enjoy a picnic at the picturesque Lake Daylesford, dine your way through the town's array of hatted restaurants or refresh your body, mind and soul in Hepburn Springs' famous mineral waters. This rural retreat is also home to the charming Koukla cafe, serving a wide selection of locally sourced favourites, sweet treats, cocktails and wine under the vine-covered verandah. Full of character and distinctive design, Hotel Frangos offers a wonderful opportunity for travellers to lose themselves within one of Victoria’s most cherished leisure regions.",
      "location_subheading": "Australia",
      "price": 219,
      "original_price": 406,
      "discount_percentage": 46,
      "link": "https://luxuryescapes.com/offer/006Ii000002I1dEIAS",
      "hero_image": "https://images.luxuryescapes.com/kwsgwgqyk0eyibiunyr",
      "image_two": "https://images.luxuryescapes.com/h1ic5mnq6ivrrzp35vp",
      "image_three": "https://images.luxuryescapes.com/nbfray4113xnvrpzuf28",
      "deal_tier": "Luxury Escapes - Tier 2",
      "min_duration": 2,
      "end_date_utc": "2025-08-21 13:59:00"
    }
  ],
  "seo": {
    "title": "Hôtels à Daylesford - Australie Hotels & Travel Guide 2024",
    "description": "Trouvez les meilleurs hôtels à Daylesford, Australia avec des offres exclusives. Réservez votre escapade parfaite avec jusqu'à 60% de réduction.",
    "keywords": [
      "daylesford hotels",
      "daylesford travel",
      "australia hotels"
    ],
    "canonical": "https://mondoexplora.com/fr/destination/daylesford",
    "hreflang": {
      "en": "https://mondoexplora.com/en/destination/daylesford",
      "es": "https://mondoexplora.com/es/destination/daylesford",
      "fr": "https://mondoexplora.com/fr/destination/daylesford",
      "it": "https://mondoexplora.com/it/destination/daylesford"
    }
  },
  "meta": {
    "last_updated": "2025-07-27",
    "hotel_count": 1,
    "average_price": 219,
    "average_discount": 46
  }
}