{
  "city": "Surat Thani",
  "country": "Thailand",
  "country_code": "TH",
  "hero_title": "Hôtels à Surat Thani",
  "description": "Découvrez les meilleurs hôtels à Surat Thani, Thailand. Trouvez des offres exclusives et des hébergements de luxe.",
  "hero_image": "https://images.luxuryescapes.com/5lwhoyz5fc4m3nsyeqk",
  "hotels": [
    {
      "vendor_name": "The Lamai Samui",
      "offer_country_name": "Thailand",
      "location_heading": "Surat Thani",
      "title": "Koh Samui Beachfront Luxury with Three Restaurants, Spa & Infinity Pool",
      "description": "Overlooking a pristine beach on Koh Samui’s east coast, wake to the sound of the ocean and embrace tranquility at this five-star oasis on the white sands of Lamai Beach. With classic oriental architecture and feng shui design, The Lamai Samui is a calming and elegant escape backed by forested mountains. Spend your days at the infinity pool or indulge in a relaxing treatment at Le Spa before retreating to your spacious room or villa. You'll find multiple dining spaces at your doorstep - try The Plate, The Ocean Pier and The Pool Bar, each serving up delicious bites paired with ocean or poolside views. With vehicle rental services available, you'll be able to travel to the furthest stretches of Koh Samui in luxury and ease.",
      "location_subheading": "Thailand",
      "price": 142,
      "original_price": 142,
      "discount_percentage": 0,
      "link": "https://luxuryescapes.com/offer/006RF00000GQTZqYAP",
      "hero_image": "https://images.luxuryescapes.com/5lwhoyz5fc4m3nsyeqk",
      "image_two": "https://images.luxuryescapes.com/kgyyl3xhzn2pmltq9glr",
      "image_three": "https://images.luxuryescapes.com/z5myivlwppvhl8dn6mg",
      "deal_tier": "Luxury Escapes - Tier 2",
      "min_duration": 1,
      "end_date_utc": "2050-12-31 12:59:00"
    }
  ],
  "seo": {
    "title": "Hôtels à Surat Thani - Thaïlande Hotels & Travel Guide 2024",
    "description": "Trouvez les meilleurs hôtels à Surat Thani, Thailand avec des offres exclusives. Réservez votre escapade parfaite avec jusqu'à 60% de réduction.",
    "keywords": [
      "surat thani hotels",
      "surat thani travel",
      "thailand hotels"
    ],
    "canonical": "https://mondoexplora.com/fr/destination/surat-thani",
    "hreflang": {
      "en": "https://mondoexplora.com/en/destination/surat-thani",
      "es": "https://mondoexplora.com/es/destination/surat-thani",
      "fr": "https://mondoexplora.com/fr/destination/surat-thani",
      "it": "https://mondoexplora.com/it/destination/surat-thani"
    }
  },
  "meta": {
    "last_updated": "2025-07-27",
    "hotel_count": 1,
    "average_price": 142,
    "average_discount": 0
  }
}